{".class":"MypyFile","_fullname":"graphiti_core.errors","future_import_flags":[],"is_partial_stub_package":false,"is_stub":false,"names":{".class":"SymbolTable","EdgeNotFoundError":{".class":"SymbolTableNode","kind":"Gdef","node":{".class":"TypeInfo","_promote":[],"abstract_attributes":[],"alt_promote":null,"bases":["graphiti_core.errors.GraphitiError"],"dataclass_transform_spec":null,"declared_metaclass":null,"defn":{".class":"ClassDef","fullname":"graphiti_core.errors.EdgeNotFoundError","name":"EdgeNotFoundError","type_vars":[]},"deletable_attributes":[],"deprecated":null,"flags":[],"fullname":"graphiti_core.errors.EdgeNotFoundError","has_param_spec_type":false,"metaclass_type":null,"metadata":{},"module_name":"graphiti_core.errors","mro":["graphiti_core.errors.EdgeNotFoundError","graphiti_core.errors.GraphitiError","builtins.Exception","builtins.BaseException","builtins.object"],"names":{".class":"SymbolTable","__init__":{".class":"SymbolTableNode","kind":"Mdef","node":{".class":"FuncDef","abstract_status":0,"arg_kinds":[0,0],"arg_names":["self","uuid"],"dataclass_transform_spec":null,"deprecated":null,"flags":["is_trivial_self"],"fullname":"graphiti_core.errors.EdgeNotFoundError.__init__","name":"__init__","type":{".class":"CallableType","arg_kinds":[0,0],"arg_names":["self","uuid"],"arg_types":["graphiti_core.errors.EdgeNotFoundError","builtins.str"],"bound_args":[],"def_extras":{"first_arg":"self"},"fallback":"builtins.function","from_concatenate":false,"implicit":false,"imprecise_arg_kinds":false,"is_ellipsis_args":false,"name":"__init__ of EdgeNotFoundError","ret_type":{".class":"NoneType"},"type_guard":null,"type_is":null,"unpack_kwargs":false,"variables":[]}}},"message":{".class":"SymbolTableNode","implicit":true,"kind":"Mdef","node":{".class":"Var","flags":["is_inferred"],"fullname":"graphiti_core.errors.EdgeNotFoundError.message","name":"message","setter_type":null,"type":"builtins.str"}}},"self_type":{".class":"TypeVarType","default":{".class":"AnyType","missing_import_name":null,"source_any":null,"type_of_any":4},"fullname":"graphiti_core.errors.EdgeNotFoundError.Self","id":0,"name":"Self","namespace":"","upper_bound":"graphiti_core.errors.EdgeNotFoundError","values":[],"variance":0},"slots":null,"tuple_type":null,"type_vars":[],"typeddict_type":null}},"EdgesNotFoundError":{".class":"SymbolTableNode","kind":"Gdef","node":{".class":"TypeInfo","_promote":[],"abstract_attributes":[],"alt_promote":null,"bases":["graphiti_core.errors.GraphitiError"],"dataclass_transform_spec":null,"declared_metaclass":null,"defn":{".class":"ClassDef","fullname":"graphiti_core.errors.EdgesNotFoundError","name":"EdgesNotFoundError","type_vars":[]},"deletable_attributes":[],"deprecated":null,"flags":[],"fullname":"graphiti_core.errors.EdgesNotFoundError","has_param_spec_type":false,"metaclass_type":null,"metadata":{},"module_name":"graphiti_core.errors","mro":["graphiti_core.errors.EdgesNotFoundError","graphiti_core.errors.GraphitiError","builtins.Exception","builtins.BaseException","builtins.object"],"names":{".class":"SymbolTable","__init__":{".class":"SymbolTableNode","kind":"Mdef","node":{".class":"FuncDef","abstract_status":0,"arg_kinds":[0,0],"arg_names":["self","uuids"],"dataclass_transform_spec":null,"deprecated":null,"flags":["is_trivial_self"],"fullname":"graphiti_core.errors.EdgesNotFoundError.__init__","name":"__init__","type":{".class":"CallableType","arg_kinds":[0,0],"arg_names":["self","uuids"],"arg_types":["graphiti_core.errors.EdgesNotFoundError",{".class":"Instance","args":["builtins.str"],"extra_attrs":null,"type_ref":"builtins.list"}],"bound_args":[],"def_extras":{"first_arg":"self"},"fallback":"builtins.function","from_concatenate":false,"implicit":false,"imprecise_arg_kinds":false,"is_ellipsis_args":false,"name":"__init__ of EdgesNotFoundError","ret_type":{".class":"NoneType"},"type_guard":null,"type_is":null,"unpack_kwargs":false,"variables":[]}}},"message":{".class":"SymbolTableNode","implicit":true,"kind":"Mdef","node":{".class":"Var","flags":["is_inferred"],"fullname":"graphiti_core.errors.EdgesNotFoundError.message","name":"message","setter_type":null,"type":"builtins.str"}}},"self_type":{".class":"TypeVarType","default":{".class":"AnyType","missing_import_name":null,"source_any":null,"type_of_any":4},"fullname":"graphiti_core.errors.EdgesNotFoundError.Self","id":0,"name":"Self","namespace":"","upper_bound":"graphiti_core.errors.EdgesNotFoundError","values":[],"variance":0},"slots":null,"tuple_type":null,"type_vars":[],"typeddict_type":null}},"EntityTypeValidationError":{".class":"SymbolTableNode","kind":"Gdef","node":{".class":"TypeInfo","_promote":[],"abstract_attributes":[],"alt_promote":null,"bases":["graphiti_core.errors.GraphitiError"],"dataclass_transform_spec":null,"declared_metaclass":null,"defn":{".class":"ClassDef","fullname":"graphiti_core.errors.EntityTypeValidationError","name":"EntityTypeValidationError","type_vars":[]},"deletable_attributes":[],"deprecated":null,"flags":[],"fullname":"graphiti_core.errors.EntityTypeValidationError","has_param_spec_type":false,"metaclass_type":null,"metadata":{},"module_name":"graphiti_core.errors","mro":["graphiti_core.errors.EntityTypeValidationError","graphiti_core.errors.GraphitiError","builtins.Exception","builtins.BaseException","builtins.object"],"names":{".class":"SymbolTable","__init__":{".class":"SymbolTableNode","kind":"Mdef","node":{".class":"FuncDef","abstract_status":0,"arg_kinds":[0,0,0],"arg_names":["self","entity_type","entity_type_attribute"],"dataclass_transform_spec":null,"deprecated":null,"flags":["is_trivial_self"],"fullname":"graphiti_core.errors.EntityTypeValidationError.__init__","name":"__init__","type":{".class":"CallableType","arg_kinds":[0,0,0],"arg_names":["self","entity_type","entity_type_attribute"],"arg_types":["graphiti_core.errors.EntityTypeValidationError","builtins.str","builtins.str"],"bound_args":[],"def_extras":{"first_arg":"self"},"fallback":"builtins.function","from_concatenate":false,"implicit":false,"imprecise_arg_kinds":false,"is_ellipsis_args":false,"name":"__init__ of EntityTypeValidationError","ret_type":{".class":"NoneType"},"type_guard":null,"type_is":null,"unpack_kwargs":false,"variables":[]}}},"message":{".class":"SymbolTableNode","implicit":true,"kind":"Mdef","node":{".class":"Var","flags":["is_inferred"],"fullname":"graphiti_core.errors.EntityTypeValidationError.message","name":"message","setter_type":null,"type":"builtins.str"}}},"self_type":{".class":"TypeVarType","default":{".class":"AnyType","missing_import_name":null,"source_any":null,"type_of_any":4},"fullname":"graphiti_core.errors.EntityTypeValidationError.Self","id":0,"name":"Self","namespace":"","upper_bound":"graphiti_core.errors.EntityTypeValidationError","values":[],"variance":0},"slots":null,"tuple_type":null,"type_vars":[],"typeddict_type":null}},"GraphitiError":{".class":"SymbolTableNode","kind":"Gdef","node":{".class":"TypeInfo","_promote":[],"abstract_attributes":[],"alt_promote":null,"bases":["builtins.Exception"],"dataclass_transform_spec":null,"declared_metaclass":null,"defn":{".class":"ClassDef","fullname":"graphiti_core.errors.GraphitiError","name":"GraphitiError","type_vars":[]},"deletable_attributes":[],"deprecated":null,"flags":[],"fullname":"graphiti_core.errors.GraphitiError","has_param_spec_type":false,"metaclass_type":null,"metadata":{},"module_name":"graphiti_core.errors","mro":["graphiti_core.errors.GraphitiError","builtins.Exception","builtins.BaseException","builtins.object"],"names":{".class":"SymbolTable"},"self_type":{".class":"TypeVarType","default":{".class":"AnyType","missing_import_name":null,"source_any":null,"type_of_any":4},"fullname":"graphiti_core.errors.GraphitiError.Self","id":0,"name":"Self","namespace":"","upper_bound":"graphiti_core.errors.GraphitiError","values":[],"variance":0},"slots":null,"tuple_type":null,"type_vars":[],"typeddict_type":null}},"GroupIdValidationError":{".class":"SymbolTableNode","kind":"Gdef","node":{".class":"TypeInfo","_promote":[],"abstract_attributes":[],"alt_promote":null,"bases":["graphiti_core.errors.GraphitiError"],"dataclass_transform_spec":null,"declared_metaclass":null,"defn":{".class":"ClassDef","fullname":"graphiti_core.errors.GroupIdValidationError","name":"GroupIdValidationError","type_vars":[]},"deletable_attributes":[],"deprecated":null,"flags":[],"fullname":"graphiti_core.errors.GroupIdValidationError","has_param_spec_type":false,"metaclass_type":null,"metadata":{},"module_name":"graphiti_core.errors","mro":["graphiti_core.errors.GroupIdValidationError","graphiti_core.errors.GraphitiError","builtins.Exception","builtins.BaseException","builtins.object"],"names":{".class":"SymbolTable","__init__":{".class":"SymbolTableNode","kind":"Mdef","node":{".class":"FuncDef","abstract_status":0,"arg_kinds":[0,0],"arg_names":["self","group_id"],"dataclass_transform_spec":null,"deprecated":null,"flags":["is_trivial_self"],"fullname":"graphiti_core.errors.GroupIdValidationError.__init__","name":"__init__","type":{".class":"CallableType","arg_kinds":[0,0],"arg_names":["self","group_id"],"arg_types":["graphiti_core.errors.GroupIdValidationError","builtins.str"],"bound_args":[],"def_extras":{"first_arg":"self"},"fallback":"builtins.function","from_concatenate":false,"implicit":false,"imprecise_arg_kinds":false,"is_ellipsis_args":false,"name":"__init__ of GroupIdValidationError","ret_type":{".class":"NoneType"},"type_guard":null,"type_is":null,"unpack_kwargs":false,"variables":[]}}},"message":{".class":"SymbolTableNode","implicit":true,"kind":"Mdef","node":{".class":"Var","flags":["is_inferred"],"fullname":"graphiti_core.errors.GroupIdValidationError.message","name":"message","setter_type":null,"type":"builtins.str"}}},"self_type":{".class":"TypeVarType","default":{".class":"AnyType","missing_import_name":null,"source_any":null,"type_of_any":4},"fullname":"graphiti_core.errors.GroupIdValidationError.Self","id":0,"name":"Self","namespace":"","upper_bound":"graphiti_core.errors.GroupIdValidationError","values":[],"variance":0},"slots":null,"tuple_type":null,"type_vars":[],"typeddict_type":null}},"GroupsEdgesNotFoundError":{".class":"SymbolTableNode","kind":"Gdef","node":{".class":"TypeInfo","_promote":[],"abstract_attributes":[],"alt_promote":null,"bases":["graphiti_core.errors.GraphitiError"],"dataclass_transform_spec":null,"declared_metaclass":null,"defn":{".class":"ClassDef","fullname":"graphiti_core.errors.GroupsEdgesNotFoundError","name":"GroupsEdgesNotFoundError","type_vars":[]},"deletable_attributes":[],"deprecated":null,"flags":[],"fullname":"graphiti_core.errors.GroupsEdgesNotFoundError","has_param_spec_type":false,"metaclass_type":null,"metadata":{},"module_name":"graphiti_core.errors","mro":["graphiti_core.errors.GroupsEdgesNotFoundError","graphiti_core.errors.GraphitiError","builtins.Exception","builtins.BaseException","builtins.object"],"names":{".class":"SymbolTable","__init__":{".class":"SymbolTableNode","kind":"Mdef","node":{".class":"FuncDef","abstract_status":0,"arg_kinds":[0,0],"arg_names":["self","group_ids"],"dataclass_transform_spec":null,"deprecated":null,"flags":["is_trivial_self"],"fullname":"graphiti_core.errors.GroupsEdgesNotFoundError.__init__","name":"__init__","type":{".class":"CallableType","arg_kinds":[0,0],"arg_names":["self","group_ids"],"arg_types":["graphiti_core.errors.GroupsEdgesNotFoundError",{".class":"Instance","args":["builtins.str"],"extra_attrs":null,"type_ref":"builtins.list"}],"bound_args":[],"def_extras":{"first_arg":"self"},"fallback":"builtins.function","from_concatenate":false,"implicit":false,"imprecise_arg_kinds":false,"is_ellipsis_args":false,"name":"__init__ of GroupsEdgesNotFoundError","ret_type":{".class":"NoneType"},"type_guard":null,"type_is":null,"unpack_kwargs":false,"variables":[]}}},"message":{".class":"SymbolTableNode","implicit":true,"kind":"Mdef","node":{".class":"Var","flags":["is_inferred"],"fullname":"graphiti_core.errors.GroupsEdgesNotFoundError.message","name":"message","setter_type":null,"type":"builtins.str"}}},"self_type":{".class":"TypeVarType","default":{".class":"AnyType","missing_import_name":null,"source_any":null,"type_of_any":4},"fullname":"graphiti_core.errors.GroupsEdgesNotFoundError.Self","id":0,"name":"Self","namespace":"","upper_bound":"graphiti_core.errors.GroupsEdgesNotFoundError","values":[],"variance":0},"slots":null,"tuple_type":null,"type_vars":[],"typeddict_type":null}},"GroupsNodesNotFoundError":{".class":"SymbolTableNode","kind":"Gdef","node":{".class":"TypeInfo","_promote":[],"abstract_attributes":[],"alt_promote":null,"bases":["graphiti_core.errors.GraphitiError"],"dataclass_transform_spec":null,"declared_metaclass":null,"defn":{".class":"ClassDef","fullname":"graphiti_core.errors.GroupsNodesNotFoundError","name":"GroupsNodesNotFoundError","type_vars":[]},"deletable_attributes":[],"deprecated":null,"flags":[],"fullname":"graphiti_core.errors.GroupsNodesNotFoundError","has_param_spec_type":false,"metaclass_type":null,"metadata":{},"module_name":"graphiti_core.errors","mro":["graphiti_core.errors.GroupsNodesNotFoundError","graphiti_core.errors.GraphitiError","builtins.Exception","builtins.BaseException","builtins.object"],"names":{".class":"SymbolTable","__init__":{".class":"SymbolTableNode","kind":"Mdef","node":{".class":"FuncDef","abstract_status":0,"arg_kinds":[0,0],"arg_names":["self","group_ids"],"dataclass_transform_spec":null,"deprecated":null,"flags":["is_trivial_self"],"fullname":"graphiti_core.errors.GroupsNodesNotFoundError.__init__","name":"__init__","type":{".class":"CallableType","arg_kinds":[0,0],"arg_names":["self","group_ids"],"arg_types":["graphiti_core.errors.GroupsNodesNotFoundError",{".class":"Instance","args":["builtins.str"],"extra_attrs":null,"type_ref":"builtins.list"}],"bound_args":[],"def_extras":{"first_arg":"self"},"fallback":"builtins.function","from_concatenate":false,"implicit":false,"imprecise_arg_kinds":false,"is_ellipsis_args":false,"name":"__init__ of GroupsNodesNotFoundError","ret_type":{".class":"NoneType"},"type_guard":null,"type_is":null,"unpack_kwargs":false,"variables":[]}}},"message":{".class":"SymbolTableNode","implicit":true,"kind":"Mdef","node":{".class":"Var","flags":["is_inferred"],"fullname":"graphiti_core.errors.GroupsNodesNotFoundError.message","name":"message","setter_type":null,"type":"builtins.str"}}},"self_type":{".class":"TypeVarType","default":{".class":"AnyType","missing_import_name":null,"source_any":null,"type_of_any":4},"fullname":"graphiti_core.errors.GroupsNodesNotFoundError.Self","id":0,"name":"Self","namespace":"","upper_bound":"graphiti_core.errors.GroupsNodesNotFoundError","values":[],"variance":0},"slots":null,"tuple_type":null,"type_vars":[],"typeddict_type":null}},"NodeNotFoundError":{".class":"SymbolTableNode","kind":"Gdef","node":{".class":"TypeInfo","_promote":[],"abstract_attributes":[],"alt_promote":null,"bases":["graphiti_core.errors.GraphitiError"],"dataclass_transform_spec":null,"declared_metaclass":null,"defn":{".class":"ClassDef","fullname":"graphiti_core.errors.NodeNotFoundError","name":"NodeNotFoundError","type_vars":[]},"deletable_attributes":[],"deprecated":null,"flags":[],"fullname":"graphiti_core.errors.NodeNotFoundError","has_param_spec_type":false,"metaclass_type":null,"metadata":{},"module_name":"graphiti_core.errors","mro":["graphiti_core.errors.NodeNotFoundError","graphiti_core.errors.GraphitiError","builtins.Exception","builtins.BaseException","builtins.object"],"names":{".class":"SymbolTable","__init__":{".class":"SymbolTableNode","kind":"Mdef","node":{".class":"FuncDef","abstract_status":0,"arg_kinds":[0,0],"arg_names":["self","uuid"],"dataclass_transform_spec":null,"deprecated":null,"flags":["is_trivial_self"],"fullname":"graphiti_core.errors.NodeNotFoundError.__init__","name":"__init__","type":{".class":"CallableType","arg_kinds":[0,0],"arg_names":["self","uuid"],"arg_types":["graphiti_core.errors.NodeNotFoundError","builtins.str"],"bound_args":[],"def_extras":{"first_arg":"self"},"fallback":"builtins.function","from_concatenate":false,"implicit":false,"imprecise_arg_kinds":false,"is_ellipsis_args":false,"name":"__init__ of NodeNotFoundError","ret_type":{".class":"NoneType"},"type_guard":null,"type_is":null,"unpack_kwargs":false,"variables":[]}}},"message":{".class":"SymbolTableNode","implicit":true,"kind":"Mdef","node":{".class":"Var","flags":["is_inferred"],"fullname":"graphiti_core.errors.NodeNotFoundError.message","name":"message","setter_type":null,"type":"builtins.str"}}},"self_type":{".class":"TypeVarType","default":{".class":"AnyType","missing_import_name":null,"source_any":null,"type_of_any":4},"fullname":"graphiti_core.errors.NodeNotFoundError.Self","id":0,"name":"Self","namespace":"","upper_bound":"graphiti_core.errors.NodeNotFoundError","values":[],"variance":0},"slots":null,"tuple_type":null,"type_vars":[],"typeddict_type":null}},"SearchRerankerError":{".class":"SymbolTableNode","kind":"Gdef","node":{".class":"TypeInfo","_promote":[],"abstract_attributes":[],"alt_promote":null,"bases":["graphiti_core.errors.GraphitiError"],"dataclass_transform_spec":null,"declared_metaclass":null,"defn":{".class":"ClassDef","fullname":"graphiti_core.errors.SearchRerankerError","name":"SearchRerankerError","type_vars":[]},"deletable_attributes":[],"deprecated":null,"flags":[],"fullname":"graphiti_core.errors.SearchRerankerError","has_param_spec_type":false,"metaclass_type":null,"metadata":{},"module_name":"graphiti_core.errors","mro":["graphiti_core.errors.SearchRerankerError","graphiti_core.errors.GraphitiError","builtins.Exception","builtins.BaseException","builtins.object"],"names":{".class":"SymbolTable","__init__":{".class":"SymbolTableNode","kind":"Mdef","node":{".class":"FuncDef","abstract_status":0,"arg_kinds":[0,0],"arg_names":["self","text"],"dataclass_transform_spec":null,"deprecated":null,"flags":["is_trivial_self"],"fullname":"graphiti_core.errors.SearchRerankerError.__init__","name":"__init__","type":{".class":"CallableType","arg_kinds":[0,0],"arg_names":["self","text"],"arg_types":["graphiti_core.errors.SearchRerankerError","builtins.str"],"bound_args":[],"def_extras":{"first_arg":"self"},"fallback":"builtins.function","from_concatenate":false,"implicit":false,"imprecise_arg_kinds":false,"is_ellipsis_args":false,"name":"__init__ of SearchRerankerError","ret_type":{".class":"NoneType"},"type_guard":null,"type_is":null,"unpack_kwargs":false,"variables":[]}}},"message":{".class":"SymbolTableNode","implicit":true,"kind":"Mdef","node":{".class":"Var","flags":["is_inferred"],"fullname":"graphiti_core.errors.SearchRerankerError.message","name":"message","setter_type":null,"type":"builtins.str"}}},"self_type":{".class":"TypeVarType","default":{".class":"AnyType","missing_import_name":null,"source_any":null,"type_of_any":4},"fullname":"graphiti_core.errors.SearchRerankerError.Self","id":0,"name":"Self","namespace":"","upper_bound":"graphiti_core.errors.SearchRerankerError","values":[],"variance":0},"slots":null,"tuple_type":null,"type_vars":[],"typeddict_type":null}},"__annotations__":{".class":"SymbolTableNode","kind":"Gdef","node":{".class":"Var","flags":["is_ready"],"fullname":"graphiti_core.errors.__annotations__","name":"__annotations__","setter_type":null,"type":{".class":"Instance","args":["builtins.str",{".class":"AnyType","missing_import_name":null,"source_any":null,"type_of_any":6}],"extra_attrs":null,"type_ref":"builtins.dict"}}},"__doc__":{".class":"SymbolTableNode","kind":"Gdef","node":{".class":"Var","flags":["is_ready"],"fullname":"graphiti_core.errors.__doc__","name":"__doc__","setter_type":null,"type":"builtins.str"}},"__file__":{".class":"SymbolTableNode","kind":"Gdef","node":{".class":"Var","flags":["is_ready"],"fullname":"graphiti_core.errors.__file__","name":"__file__","setter_type":null,"type":"builtins.str"}},"__name__":{".class":"SymbolTableNode","kind":"Gdef","node":{".class":"Var","flags":["is_ready"],"fullname":"graphiti_core.errors.__name__","name":"__name__","setter_type":null,"type":"builtins.str"}},"__package__":{".class":"SymbolTableNode","kind":"Gdef","node":{".class":"Var","flags":["is_ready"],"fullname":"graphiti_core.errors.__package__","name":"__package__","setter_type":null,"type":"builtins.str"}},"__spec__":{".class":"SymbolTableNode","kind":"Gdef","node":{".class":"Var","flags":["is_ready"],"fullname":"graphiti_core.errors.__spec__","name":"__spec__","setter_type":null,"type":"_frozen_importlib.ModuleSpec"}}},"path":"/opt/anaconda3/lib/python3.11/site-packages/graphiti_core/errors.py"}