{".class":"MypyFile","_fullname":"api.services.dynamics_service","future_import_flags":[],"is_partial_stub_package":false,"is_stub":false,"names":{".class":"SymbolTable","DynamicsService":{".class":"SymbolTableNode","kind":"Gdef","node":{".class":"TypeInfo","_promote":[],"abstract_attributes":[],"alt_promote":null,"bases":["builtins.object"],"dataclass_transform_spec":null,"declared_metaclass":null,"defn":{".class":"ClassDef","fullname":"api.services.dynamics_service.DynamicsService","name":"DynamicsService","type_vars":[]},"deletable_attributes":[],"deprecated":null,"flags":[],"fullname":"api.services.dynamics_service.DynamicsService","has_param_spec_type":false,"metaclass_type":null,"metadata":{},"module_name":"api.services.dynamics_service","mro":["api.services.dynamics_service.DynamicsService","builtins.object"],"names":{".class":"SymbolTable","alogistic":{".class":"SymbolTableNode","kind":"Mdef","node":{".class":"Decorator","func":{".class":"FuncDef","abstract_status":0,"arg_kinds":[0,0,0,0],"arg_names":["sigm","tau","input_values","weights"],"dataclass_transform_spec":null,"deprecated":null,"flags":["is_static","is_decorated"],"fullname":"api.services.dynamics_service.DynamicsService.alogistic","name":"alogistic","type":{".class":"CallableType","arg_kinds":[0,0,0,0],"arg_names":["sigm","tau","input_values","weights"],"arg_types":["builtins.float","builtins.float",{".class":"Instance","args":["builtins.float"],"extra_attrs":null,"type_ref":"builtins.list"},{".class":"Instance","args":["builtins.float"],"extra_attrs":null,"type_ref":"builtins.list"}],"bound_args":[],"def_extras":{"first_arg":null},"fallback":"builtins.function","from_concatenate":false,"implicit":false,"imprecise_arg_kinds":false,"is_ellipsis_args":false,"name":"alogistic of DynamicsService","ret_type":"builtins.float","type_guard":null,"type_is":null,"unpack_kwargs":false,"variables":[]}},"is_overload":false,"var":{".class":"Var","flags":["is_initialized_in_class","is_staticmethod","is_ready","is_inferred"],"fullname":"api.services.dynamics_service.DynamicsService.alogistic","name":"alogistic","setter_type":null,"type":{".class":"CallableType","arg_kinds":[0,0,0,0],"arg_names":["sigm","tau","input_values","weights"],"arg_types":["builtins.float","builtins.float",{".class":"Instance","args":["builtins.float"],"extra_attrs":null,"type_ref":"builtins.list"},{".class":"Instance","args":["builtins.float"],"extra_attrs":null,"type_ref":"builtins.list"}],"bound_args":[],"def_extras":{"first_arg":null},"fallback":"builtins.function","from_concatenate":false,"implicit":false,"imprecise_arg_kinds":false,"is_ellipsis_args":false,"name":"alogistic of DynamicsService","ret_type":"builtins.float","type_guard":null,"type_is":null,"unpack_kwargs":false,"variables":[]}}}},"hebbian":{".class":"SymbolTableNode","kind":"Mdef","node":{".class":"Decorator","func":{".class":"FuncDef","abstract_status":0,"arg_kinds":[0,0,0,0],"arg_names":["mu","x","y","w"],"dataclass_transform_spec":null,"deprecated":null,"flags":["is_static","is_decorated"],"fullname":"api.services.dynamics_service.DynamicsService.hebbian","name":"hebbian","type":{".class":"CallableType","arg_kinds":[0,0,0,0],"arg_names":["mu","x","y","w"],"arg_types":["builtins.float","builtins.float","builtins.float","builtins.float"],"bound_args":[],"def_extras":{"first_arg":null},"fallback":"builtins.function","from_concatenate":false,"implicit":false,"imprecise_arg_kinds":false,"is_ellipsis_args":false,"name":"hebbian of DynamicsService","ret_type":"builtins.float","type_guard":null,"type_is":null,"unpack_kwargs":false,"variables":[]}},"is_overload":false,"var":{".class":"Var","flags":["is_initialized_in_class","is_staticmethod","is_ready","is_inferred"],"fullname":"api.services.dynamics_service.DynamicsService.hebbian","name":"hebbian","setter_type":null,"type":{".class":"CallableType","arg_kinds":[0,0,0,0],"arg_names":["mu","x","y","w"],"arg_types":["builtins.float","builtins.float","builtins.float","builtins.float"],"bound_args":[],"def_extras":{"first_arg":null},"fallback":"builtins.function","from_concatenate":false,"implicit":false,"imprecise_arg_kinds":false,"is_ellipsis_args":false,"name":"hebbian of DynamicsService","ret_type":"builtins.float","type_guard":null,"type_is":null,"unpack_kwargs":false,"variables":[]}}}},"state_update":{".class":"SymbolTableNode","kind":"Mdef","node":{".class":"Decorator","func":{".class":"FuncDef","abstract_status":0,"arg_kinds":[0,0,0,1],"arg_names":["current_val","impact","speed_factor","delta_t"],"dataclass_transform_spec":null,"deprecated":null,"flags":["is_static","is_decorated"],"fullname":"api.services.dynamics_service.DynamicsService.state_update","name":"state_update","type":{".class":"CallableType","arg_kinds":[0,0,0,1],"arg_names":["current_val","impact","speed_factor","delta_t"],"arg_types":["builtins.float","builtins.float","builtins.float","builtins.float"],"bound_args":[],"def_extras":{"first_arg":null},"fallback":"builtins.function","from_concatenate":false,"implicit":false,"imprecise_arg_kinds":false,"is_ellipsis_args":false,"name":"state_update of DynamicsService","ret_type":"builtins.float","type_guard":null,"type_is":null,"unpack_kwargs":false,"variables":[]}},"is_overload":false,"var":{".class":"Var","flags":["is_initialized_in_class","is_staticmethod","is_ready","is_inferred"],"fullname":"api.services.dynamics_service.DynamicsService.state_update","name":"state_update","setter_type":null,"type":{".class":"CallableType","arg_kinds":[0,0,0,1],"arg_names":["current_val","impact","speed_factor","delta_t"],"arg_types":["builtins.float","builtins.float","builtins.float","builtins.float"],"bound_args":[],"def_extras":{"first_arg":null},"fallback":"builtins.function","from_concatenate":false,"implicit":false,"imprecise_arg_kinds":false,"is_ellipsis_args":false,"name":"state_update of DynamicsService","ret_type":"builtins.float","type_guard":null,"type_is":null,"unpack_kwargs":false,"variables":[]}}}}},"self_type":{".class":"TypeVarType","default":{".class":"AnyType","missing_import_name":null,"source_any":null,"type_of_any":4},"fullname":"api.services.dynamics_service.DynamicsService.Self","id":0,"name":"Self","namespace":"","upper_bound":"api.services.dynamics_service.DynamicsService","values":[],"variance":0},"slots":null,"tuple_type":null,"type_vars":[],"typeddict_type":null}},"List":{".class":"SymbolTableNode","cross_ref":"typing.List","kind":"Gdef"},"__annotations__":{".class":"SymbolTableNode","kind":"Gdef","node":{".class":"Var","flags":["is_ready"],"fullname":"api.services.dynamics_service.__annotations__","name":"__annotations__","setter_type":null,"type":{".class":"Instance","args":["builtins.str",{".class":"AnyType","missing_import_name":null,"source_any":null,"type_of_any":6}],"extra_attrs":null,"type_ref":"builtins.dict"}}},"__doc__":{".class":"SymbolTableNode","kind":"Gdef","node":{".class":"Var","flags":["is_ready"],"fullname":"api.services.dynamics_service.__doc__","name":"__doc__","setter_type":null,"type":"builtins.str"}},"__file__":{".class":"SymbolTableNode","kind":"Gdef","node":{".class":"Var","flags":["is_ready"],"fullname":"api.services.dynamics_service.__file__","name":"__file__","setter_type":null,"type":"builtins.str"}},"__name__":{".class":"SymbolTableNode","kind":"Gdef","node":{".class":"Var","flags":["is_ready"],"fullname":"api.services.dynamics_service.__name__","name":"__name__","setter_type":null,"type":"builtins.str"}},"__package__":{".class":"SymbolTableNode","kind":"Gdef","node":{".class":"Var","flags":["is_ready"],"fullname":"api.services.dynamics_service.__package__","name":"__package__","setter_type":null,"type":"builtins.str"}},"__spec__":{".class":"SymbolTableNode","kind":"Gdef","node":{".class":"Var","flags":["is_ready"],"fullname":"api.services.dynamics_service.__spec__","name":"__spec__","setter_type":null,"type":"_frozen_importlib.ModuleSpec"}},"np":{".class":"SymbolTableNode","cross_ref":"numpy","kind":"Gdef"}},"path":"/Volumes/Asylum/dev/dionysus3-core/api/services/dynamics_service.py"}